bumpwright/__init__.py
bumpwright/compare.py
bumpwright/config.py
bumpwright/gitutils.py
bumpwright/public_api.py
bumpwright/types.py
bumpwright/version_schemes.py
bumpwright/versioning.py
bumpwright/analysers/__init__.py
bumpwright/analysers/cli.py
bumpwright/analysers/graphql_schema.py
bumpwright/analysers/grpc.py
bumpwright/analysers/migrations.py
bumpwright/analysers/openapi.py
bumpwright/analysers/utils.py
bumpwright/analysers/web_routes.py
bumpwright/cli/__init__.py
bumpwright/cli/__main__.py
bumpwright/cli/bump.py
bumpwright/cli/changelog.py
bumpwright/cli/decide.py
bumpwright/cli/history.py
bumpwright/cli/init.py
bumpwright/templates/changelog.md.j2
bumpwright-7.2.0.dist-info/licenses/LICENSE
bumpwright-7.2.0.dist-info/METADATA
bumpwright-7.2.0.dist-info/WHEEL
bumpwright-7.2.0.dist-info/entry_points.txt
bumpwright-7.2.0.dist-info/top_level.txt
bumpwright-7.2.0.dist-info/RECORD
