Metadata-Version: 2.4
Name: bumpwright
Version: 7.2.0
Summary: Static public-API diff + heuristics to suggest semantic version bumps.
Author-email: Lewis Morris <lewis@arched.dev>
License: MIT License
Project-URL: homepage, https://github.com/arched-dev/bumpwright
Project-URL: repository, https://github.com/arched-dev/bumpwright
Project-URL: documentation, https://bumpwright.readthedocs.io
Project-URL: bug_tracker, https://github.com/arched-dev/bumpwright/issues
Keywords: semantic-versioning,semver,api,diff,release
Classifier: Development Status :: 3 - Alpha
Classifier: Intended Audience :: Developers
Classifier: License :: OSI Approved :: MIT License
Classifier: Operating System :: OS Independent
Classifier: Programming Language :: Python :: 3
Classifier: Programming Language :: Python :: 3 :: Only
Classifier: Programming Language :: Python :: 3.11
Classifier: Programming Language :: Python :: 3.12
Classifier: Programming Language :: Python :: 3.13
Classifier: Topic :: Software Development :: Version Control
Requires-Python: >=3.11
License-File: LICENSE
Requires-Dist: libcst>=1.4.0
Requires-Dist: tomlkit>=0.13.2
Requires-Dist: jinja2>=3.1
Requires-Dist: pyyaml>=6.0
Requires-Dist: graphql-core>=3.2
Provides-Extra: test
Requires-Dist: pytest; extra == "test"
Requires-Dist: flask; extra == "test"
Requires-Dist: fastapi; extra == "test"
Requires-Dist: alembic; extra == "test"
Requires-Dist: sqlalchemy; extra == "test"
Requires-Dist: tomlkit; extra == "test"
Requires-Dist: click; extra == "test"
Provides-Extra: docs
Requires-Dist: sphinx>=7.3; extra == "docs"
Requires-Dist: sphinx-wagtail-theme; extra == "docs"
Requires-Dist: sphinx-autodoc-typehints>=2.2; extra == "docs"
Requires-Dist: sphinx-copybutton>=0.5.2; extra == "docs"
Requires-Dist: myst-parser; extra == "docs"
Requires-Dist: sphinx-click; extra == "docs"
Requires-Dist: sphinxcontrib-mermaid; extra == "docs"
Requires-Dist: sphinx-inline-tabs; extra == "docs"
Requires-Dist: sphinx_design; extra == "docs"
Provides-Extra: dev
Requires-Dist: pytest>=8.2; extra == "dev"
Requires-Dist: pytest-cov>=5.0; extra == "dev"
Requires-Dist: ruff>=0.5; extra == "dev"
Requires-Dist: black>=24.0; extra == "dev"
Requires-Dist: isort>=5.12; extra == "dev"
Requires-Dist: anybadge>=1.14; extra == "dev"
Dynamic: license-file
